estimatePDF/DensityEstimate.py
estimatePDF/DualPolyRegPDF.py
estimatePDF/ProbabilityDensityFunction.py
estimatePDF/__init__.py
estimatepdf-0.1.0.dist-info/LICENSE
estimatepdf-0.1.0.dist-info/METADATA
estimatepdf-0.1.0.dist-info/WHEEL
estimatepdf-0.1.0.dist-info/top_level.txt
estimatepdf-0.1.0.dist-info/RECORD
