Metadata-Version: 2.1
Name: estimatePDF
Version: 0.1.0
Summary: Probability Density Function Estimation Library
Home-page: https://github.com/ShanSarkar75/estimatePDF
Author: Shantanu Sarkar
Author-email: Shantanu Sarkar <shantanu75@gmail.com>
License: MIT
Project-URL: Homepage, https://github.com/ShanSarkar75/estimatePDF
Project-URL: Documentation, https://github.com/ShanSarkar75/estimatePDF#readme
Project-URL: Repository, https://github.com/ShanSarkar75/estimatePDF
Project-URL: BugTracker, https://github.com/ShanSarkar75/estimatePDF/issues
Keywords: PDF,probability density,statistics,Python,data science
Classifier: Programming Language :: Python :: 3
Classifier: License :: OSI Approved :: MIT License
Classifier: Intended Audience :: Science/Research
Classifier: Topic :: Scientific/Engineering :: Mathematics
Requires-Python: >=3.8
License-File: LICENSE
Requires-Dist: numpy
Requires-Dist: scipy
Requires-Dist: pandas
Requires-Dist: matplotlib
Requires-Dist: tensorflow
